pyroll/pillar_model_archard/__init__.py
pyroll/pillar_model_archard/report.py
pyroll/pillar_model_archard/roll_pass.py
pyroll_pillar_model_archard-3.0.0.dev2.dist-info/METADATA
pyroll_pillar_model_archard-3.0.0.dev2.dist-info/WHEEL
pyroll_pillar_model_archard-3.0.0.dev2.dist-info/licenses/LICENSE
pyroll_pillar_model_archard-3.0.0.dev2.dist-info/RECORD
