Metadata-Version: 2.4
Name: pyroll-pillar-model-archard
Version: 3.0.0.dev2
Summary: Plugin for PyRolL providing a pillar wise implementation of archards wear equation.
Project-URL: Homepage, https://pyroll.readthedocs.io
Project-URL: Repository, https://github.com/pyroll-project/pyroll-pillar-model-archard
Project-URL: Documentation, https://github.com/pyroll-project/pyroll-pillar-model-archard/blob/main/docs/docs.pdf
Author-email: Christoph Renzing <christoph.renzing@imf.tu-freiberg.de>
License-Expression: BSD-3-Clause
License-File: LICENSE
Classifier: Intended Audience :: Manufacturing
Classifier: Intended Audience :: Science/Research
Classifier: Operating System :: OS Independent
Classifier: Topic :: Scientific/Engineering
Requires-Python: <4.0,>=3.9
Requires-Dist: pyroll-core~=3.0
Requires-Dist: pyroll-freiberg-flow-stress~=3.0
Requires-Dist: pyroll-hensel-force-torque~=3.0
Requires-Dist: pyroll-pillar-model~=3.0
